taskid/__init__.py
taskid/input.py
taskid/json_encoder.py
taskid/middleware.py
taskid/task.py
taskid/taskid.py
taskid/text_input.py
taskid_client/__init__.py
taskid_client/input.py
taskid_client/json_encoder.py
taskid_client/middleware.py
taskid_client/task.py
taskid_client/taskid.py
taskid_client/text_input.py
taskid-0.1.2.dist-info/LICENSE
taskid-0.1.2.dist-info/METADATA
taskid-0.1.2.dist-info/WHEEL
taskid-0.1.2.dist-info/top_level.txt
taskid-0.1.2.dist-info/RECORD
